{
  "metadata" : {
    "identifier" : "https://www.nettruyento.com/truyen-tranh/ta-co-mot-son-trai-370810",
    "title" : "Ta Có Một Sơn Trại - Chapter 158",
    "subtitle" : null,
    "author" : null,
    "narrator" : null,
    "language" : "vi",
    "description" : null,
    "publisher" : "N/A",
    "subject" : null,
    "modified" : null,
    "published" : "2023-06-10",
    "duration" : 0,
    "abridged" : false,
    "conformsTo" : "https://readium.org/webpub-manifest/profiles/divina",
    "numberOfPages" : 577,
    "readingProgression" : "ttb",
    "belongsTo" : null,
    "presentation" : {
      "fit" : "width",
      "overflow" : "scrolled",
      "continuous" : true
    },
    "@type" : null,
    "schema:license" : null
  },
  "links" : [ {
    "rel" : "self",
    "href" : "https://raw.githubusercontent.com/thuvienonline40/book_storage_collection/main/comic_manifest.json",
    "type" : "application/divina+json"
  } ],
  "readingOrder" : [ {
    "href" : "https://raw.githubusercontent.com/quetcccd/comic_storage7/main/IMAGE/IMAGE_3aa7cfaaae4b851a2a2ae1f4411dea9e_2c6acac7bf419c61f5f52672d84294b5_e2d17a98753533995ebbef3204cd1827.jpg",
    "type" : "image/jpeg",
    "bitrate" : 0,
    "duration" : 0,
    "title" : null,
    "properties" : null,
    "alternate" : [ {
      "href" : "https://i338.ntcdntempv3.com/data/images/37081/791604/001.jpg?data=net",
      "type" : "image/jpeg",
      "bitrate" : 0,
      "duration" : 0,
      "title" : null,
      "properties" : null,
      "alternate" : null
    } ]
  }, {
    "href" : "https://raw.githubusercontent.com/quetcccd/comic_storage7/main/IMAGE/IMAGE_3aa7cfaaae4b851a2a2ae1f4411dea9e_2c6acac7bf419c61f5f52672d84294b5_594ab4d3893ce9474f10cd54f5c459ca.jpg",
    "type" : "image/jpeg",
    "bitrate" : 0,
    "duration" : 0,
    "title" : null,
    "properties" : null,
    "alternate" : [ {
      "href" : "https://i338.ntcdntempv3.com/data/images/37081/791604/002.jpg?data=net",
      "type" : "image/jpeg",
      "bitrate" : 0,
      "duration" : 0,
      "title" : null,
      "properties" : null,
      "alternate" : null
    } ]
  }, {
    "href" : "https://raw.githubusercontent.com/quetcccd/comic_storage7/main/IMAGE/IMAGE_3aa7cfaaae4b851a2a2ae1f4411dea9e_2c6acac7bf419c61f5f52672d84294b5_a4e5f66580ad825fad19d2ff0b1f5944.jpg",
    "type" : "image/jpeg",
    "bitrate" : 0,
    "duration" : 0,
    "title" : null,
    "properties" : null,
    "alternate" : [ {
      "href" : "https://i338.ntcdntempv3.com/data/images/37081/791604/003.jpg?data=net",
      "type" : "image/jpeg",
      "bitrate" : 0,
      "duration" : 0,
      "title" : null,
      "properties" : null,
      "alternate" : null
    } ]
  }, {
    "href" : "https://raw.githubusercontent.com/quetcccd/comic_storage7/main/IMAGE/IMAGE_3aa7cfaaae4b851a2a2ae1f4411dea9e_2c6acac7bf419c61f5f52672d84294b5_cc99f5e3914b77ccf88fcb5bd611a096.jpg",
    "type" : "image/jpeg",
    "bitrate" : 0,
    "duration" : 0,
    "title" : null,
    "properties" : null,
    "alternate" : [ {
      "href" : "https://i338.ntcdntempv3.com/data/images/37081/791604/004.jpg?data=net",
      "type" : "image/jpeg",
      "bitrate" : 0,
      "duration" : 0,
      "title" : null,
      "properties" : null,
      "alternate" : null
    } ]
  }, {
    "href" : "https://raw.githubusercontent.com/quetcccd/comic_storage7/main/IMAGE/IMAGE_3aa7cfaaae4b851a2a2ae1f4411dea9e_2c6acac7bf419c61f5f52672d84294b5_a6c3b96404fe4432de08813511689fc1.jpg",
    "type" : "image/jpeg",
    "bitrate" : 0,
    "duration" : 0,
    "title" : null,
    "properties" : null,
    "alternate" : [ {
      "href" : "https://i338.ntcdntempv3.com/data/images/37081/791604/005.jpg?data=net",
      "type" : "image/jpeg",
      "bitrate" : 0,
      "duration" : 0,
      "title" : null,
      "properties" : null,
      "alternate" : null
    } ]
  }, {
    "href" : "https://raw.githubusercontent.com/quetcccd/comic_storage7/main/IMAGE/IMAGE_3aa7cfaaae4b851a2a2ae1f4411dea9e_2c6acac7bf419c61f5f52672d84294b5_d09bfb57f4923d0258ca9925ba59dd74.jpg",
    "type" : "image/jpeg",
    "bitrate" : 0,
    "duration" : 0,
    "title" : null,
    "properties" : null,
    "alternate" : [ {
      "href" : "https://i338.ntcdntempv3.com/data/images/37081/791604/006.jpg?data=net",
      "type" : "image/jpeg",
      "bitrate" : 0,
      "duration" : 0,
      "title" : null,
      "properties" : null,
      "alternate" : null
    } ]
  }, {
    "href" : "https://raw.githubusercontent.com/quetcccd/comic_storage7/main/IMAGE/IMAGE_3aa7cfaaae4b851a2a2ae1f4411dea9e_2c6acac7bf419c61f5f52672d84294b5_6a4d8dd3e04a75c02b0c9e980cd1d9c1.jpg",
    "type" : "image/jpeg",
    "bitrate" : 0,
    "duration" : 0,
    "title" : null,
    "properties" : null,
    "alternate" : [ {
      "href" : "https://i338.ntcdntempv3.com/data/images/37081/791604/007.jpg?data=net",
      "type" : "image/jpeg",
      "bitrate" : 0,
      "duration" : 0,
      "title" : null,
      "properties" : null,
      "alternate" : null
    } ]
  }, {
    "href" : "https://raw.githubusercontent.com/quetcccd/comic_storage7/main/IMAGE/IMAGE_3aa7cfaaae4b851a2a2ae1f4411dea9e_2c6acac7bf419c61f5f52672d84294b5_33ba43ebb9528feef0982fea964f3807.jpg",
    "type" : "image/jpeg",
    "bitrate" : 0,
    "duration" : 0,
    "title" : null,
    "properties" : null,
    "alternate" : [ {
      "href" : "https://i338.ntcdntempv3.com/data/images/37081/791604/008.jpg?data=net",
      "type" : "image/jpeg",
      "bitrate" : 0,
      "duration" : 0,
      "title" : null,
      "properties" : null,
      "alternate" : null
    } ]
  }, {
    "href" : "https://raw.githubusercontent.com/quetcccd/comic_storage7/main/IMAGE/IMAGE_3aa7cfaaae4b851a2a2ae1f4411dea9e_2c6acac7bf419c61f5f52672d84294b5_845e68faf7faf4d1cb6b191a03e09422.jpg",
    "type" : "image/jpeg",
    "bitrate" : 0,
    "duration" : 0,
    "title" : null,
    "properties" : null,
    "alternate" : [ {
      "href" : "https://i338.ntcdntempv3.com/data/images/37081/791604/009.jpg?data=net",
      "type" : "image/jpeg",
      "bitrate" : 0,
      "duration" : 0,
      "title" : null,
      "properties" : null,
      "alternate" : null
    } ]
  }, {
    "href" : "https://raw.githubusercontent.com/quetcccd/comic_storage7/main/IMAGE/IMAGE_3aa7cfaaae4b851a2a2ae1f4411dea9e_2c6acac7bf419c61f5f52672d84294b5_d7a2caf21c07e1bedbf7f3b47d1ec248.jpg",
    "type" : "image/jpeg",
    "bitrate" : 0,
    "duration" : 0,
    "title" : null,
    "properties" : null,
    "alternate" : [ {
      "href" : "https://i338.ntcdntempv3.com/data/images/37081/791604/010.jpg?data=net",
      "type" : "image/jpeg",
      "bitrate" : 0,
      "duration" : 0,
      "title" : null,
      "properties" : null,
      "alternate" : null
    } ]
  }, {
    "href" : "https://raw.githubusercontent.com/quetcccd/comic_storage7/main/IMAGE/IMAGE_3aa7cfaaae4b851a2a2ae1f4411dea9e_2c6acac7bf419c61f5f52672d84294b5_f5bf2eac55edd3e55f0daa3cbc1974ea.jpg",
    "type" : "image/jpeg",
    "bitrate" : 0,
    "duration" : 0,
    "title" : null,
    "properties" : null,
    "alternate" : [ {
      "href" : "https://i338.ntcdntempv3.com/data/images/37081/791604/011.jpg?data=net",
      "type" : "image/jpeg",
      "bitrate" : 0,
      "duration" : 0,
      "title" : null,
      "properties" : null,
      "alternate" : null
    } ]
  }, {
    "href" : "https://raw.githubusercontent.com/quetcccd/comic_storage7/main/IMAGE/IMAGE_3aa7cfaaae4b851a2a2ae1f4411dea9e_2c6acac7bf419c61f5f52672d84294b5_11f1e691101d5a7749795c4c441a9030.jpg",
    "type" : "image/jpeg",
    "bitrate" : 0,
    "duration" : 0,
    "title" : null,
    "properties" : null,
    "alternate" : [ {
      "href" : "https://i338.ntcdntempv3.com/data/images/37081/791604/012.jpg?data=net",
      "type" : "image/jpeg",
      "bitrate" : 0,
      "duration" : 0,
      "title" : null,
      "properties" : null,
      "alternate" : null
    } ]
  }, {
    "href" : "https://raw.githubusercontent.com/quetcccd/comic_storage7/main/IMAGE/IMAGE_3aa7cfaaae4b851a2a2ae1f4411dea9e_2c6acac7bf419c61f5f52672d84294b5_44acd013ff4e0e6f7c988aec95993de5.jpg",
    "type" : "image/jpeg",
    "bitrate" : 0,
    "duration" : 0,
    "title" : null,
    "properties" : null,
    "alternate" : [ {
      "href" : "https://i338.ntcdntempv3.com/data/images/37081/791604/013.jpg?data=net",
      "type" : "image/jpeg",
      "bitrate" : 0,
      "duration" : 0,
      "title" : null,
      "properties" : null,
      "alternate" : null
    } ]
  }, {
    "href" : "https://raw.githubusercontent.com/quetcccd/comic_storage7/main/IMAGE/IMAGE_3aa7cfaaae4b851a2a2ae1f4411dea9e_2c6acac7bf419c61f5f52672d84294b5_b53fc212f7d081c209a0af9c7184232d.jpg",
    "type" : "image/jpeg",
    "bitrate" : 0,
    "duration" : 0,
    "title" : null,
    "properties" : null,
    "alternate" : [ {
      "href" : "https://i338.ntcdntempv3.com/data/images/37081/791604/014.jpg?data=net",
      "type" : "image/jpeg",
      "bitrate" : 0,
      "duration" : 0,
      "title" : null,
      "properties" : null,
      "alternate" : null
    } ]
  }, {
    "href" : "https://raw.githubusercontent.com/quetcccd/comic_storage7/main/IMAGE/IMAGE_3aa7cfaaae4b851a2a2ae1f4411dea9e_2c6acac7bf419c61f5f52672d84294b5_158eb071234953ce569b7f41a88114b3.jpg",
    "type" : "image/jpeg",
    "bitrate" : 0,
    "duration" : 0,
    "title" : null,
    "properties" : null,
    "alternate" : [ {
      "href" : "https://i338.ntcdntempv3.com/data/images/37081/791604/015.jpg?data=net",
      "type" : "image/jpeg",
      "bitrate" : 0,
      "duration" : 0,
      "title" : null,
      "properties" : null,
      "alternate" : null
    } ]
  }, {
    "href" : "https://raw.githubusercontent.com/quetcccd/comic_storage7/main/IMAGE/IMAGE_3aa7cfaaae4b851a2a2ae1f4411dea9e_2c6acac7bf419c61f5f52672d84294b5_4e3306606ba7bed956c32b629a115dea.jpg",
    "type" : "image/jpeg",
    "bitrate" : 0,
    "duration" : 0,
    "title" : null,
    "properties" : null,
    "alternate" : [ {
      "href" : "https://i338.ntcdntempv3.com/data/images/37081/791604/016.jpg?data=net",
      "type" : "image/jpeg",
      "bitrate" : 0,
      "duration" : 0,
      "title" : null,
      "properties" : null,
      "alternate" : null
    } ]
  }, {
    "href" : "https://raw.githubusercontent.com/quetcccd/comic_storage7/main/IMAGE/IMAGE_3aa7cfaaae4b851a2a2ae1f4411dea9e_2c6acac7bf419c61f5f52672d84294b5_427e41bf6fe62ee7de7699ab17905b25.jpg",
    "type" : "image/jpeg",
    "bitrate" : 0,
    "duration" : 0,
    "title" : null,
    "properties" : null,
    "alternate" : [ {
      "href" : "https://i338.ntcdntempv3.com/data/images/37081/791604/017.jpg?data=net",
      "type" : "image/jpeg",
      "bitrate" : 0,
      "duration" : 0,
      "title" : null,
      "properties" : null,
      "alternate" : null
    } ]
  }, {
    "href" : "https://raw.githubusercontent.com/quetcccd/comic_storage7/main/IMAGE/IMAGE_3aa7cfaaae4b851a2a2ae1f4411dea9e_2c6acac7bf419c61f5f52672d84294b5_476650cd8b57e1f99a07c29baf6698ed.jpg",
    "type" : "image/jpeg",
    "bitrate" : 0,
    "duration" : 0,
    "title" : null,
    "properties" : null,
    "alternate" : [ {
      "href" : "https://i338.ntcdntempv3.com/data/images/37081/791604/018.jpg?data=net",
      "type" : "image/jpeg",
      "bitrate" : 0,
      "duration" : 0,
      "title" : null,
      "properties" : null,
      "alternate" : null
    } ]
  }, {
    "href" : "https://raw.githubusercontent.com/quetcccd/comic_storage7/main/IMAGE/IMAGE_3aa7cfaaae4b851a2a2ae1f4411dea9e_2c6acac7bf419c61f5f52672d84294b5_77f448d37c1c49945e8c0802649581ab.jpg",
    "type" : "image/jpeg",
    "bitrate" : 0,
    "duration" : 0,
    "title" : null,
    "properties" : null,
    "alternate" : [ {
      "href" : "https://i338.ntcdntempv3.com/data/images/37081/791604/019.jpg?data=net",
      "type" : "image/jpeg",
      "bitrate" : 0,
      "duration" : 0,
      "title" : null,
      "properties" : null,
      "alternate" : null
    } ]
  }, {
    "href" : "https://raw.githubusercontent.com/quetcccd/comic_storage7/main/IMAGE/IMAGE_3aa7cfaaae4b851a2a2ae1f4411dea9e_2c6acac7bf419c61f5f52672d84294b5_0b4cd8c1504a1eb93e66813113023910.jpg",
    "type" : "image/jpeg",
    "bitrate" : 0,
    "duration" : 0,
    "title" : null,
    "properties" : null,
    "alternate" : [ {
      "href" : "https://i338.ntcdntempv3.com/data/images/37081/791604/020.jpg?data=net",
      "type" : "image/jpeg",
      "bitrate" : 0,
      "duration" : 0,
      "title" : null,
      "properties" : null,
      "alternate" : null
    } ]
  }, {
    "href" : "https://raw.githubusercontent.com/quetcccd/comic_storage7/main/IMAGE/IMAGE_3aa7cfaaae4b851a2a2ae1f4411dea9e_2c6acac7bf419c61f5f52672d84294b5_3f27771f7495ee31068b799462f3bf7a.jpg",
    "type" : "image/jpeg",
    "bitrate" : 0,
    "duration" : 0,
    "title" : null,
    "properties" : null,
    "alternate" : [ {
      "href" : "https://i338.ntcdntempv3.com/data/images/37081/791604/021.jpg?data=net",
      "type" : "image/jpeg",
      "bitrate" : 0,
      "duration" : 0,
      "title" : null,
      "properties" : null,
      "alternate" : null
    } ]
  }, {
    "href" : "https://raw.githubusercontent.com/quetcccd/comic_storage7/main/IMAGE/IMAGE_3aa7cfaaae4b851a2a2ae1f4411dea9e_2c6acac7bf419c61f5f52672d84294b5_0c97fe96b42396064a169fb930987a5f.jpg",
    "type" : "image/jpeg",
    "bitrate" : 0,
    "duration" : 0,
    "title" : null,
    "properties" : null,
    "alternate" : [ {
      "href" : "https://i338.ntcdntempv3.com/data/images/37081/791604/022.jpg?data=net",
      "type" : "image/jpeg",
      "bitrate" : 0,
      "duration" : 0,
      "title" : null,
      "properties" : null,
      "alternate" : null
    } ]
  }, {
    "href" : "https://raw.githubusercontent.com/quetcccd/comic_storage7/main/IMAGE/IMAGE_3aa7cfaaae4b851a2a2ae1f4411dea9e_2c6acac7bf419c61f5f52672d84294b5_ca1246628226f759a590c93c49f61c75.jpg",
    "type" : "image/jpeg",
    "bitrate" : 0,
    "duration" : 0,
    "title" : null,
    "properties" : null,
    "alternate" : [ {
      "href" : "https://i338.ntcdntempv3.com/data/images/37081/791604/023.jpg?data=net",
      "type" : "image/jpeg",
      "bitrate" : 0,
      "duration" : 0,
      "title" : null,
      "properties" : null,
      "alternate" : null
    } ]
  }, {
    "href" : "https://raw.githubusercontent.com/quetcccd/comic_storage7/main/IMAGE/IMAGE_3aa7cfaaae4b851a2a2ae1f4411dea9e_2c6acac7bf419c61f5f52672d84294b5_21329c3b28f00fa286d4db7e78eecc8b.jpg",
    "type" : "image/jpeg",
    "bitrate" : 0,
    "duration" : 0,
    "title" : null,
    "properties" : null,
    "alternate" : [ {
      "href" : "https://i338.ntcdntempv3.com/data/images/37081/791604/024.jpg?data=net",
      "type" : "image/jpeg",
      "bitrate" : 0,
      "duration" : 0,
      "title" : null,
      "properties" : null,
      "alternate" : null
    } ]
  }, {
    "href" : "https://raw.githubusercontent.com/quetcccd/comic_storage7/main/IMAGE/IMAGE_3aa7cfaaae4b851a2a2ae1f4411dea9e_2c6acac7bf419c61f5f52672d84294b5_8bbb3ee6717a669d3f925743d214e4ab.jpg",
    "type" : "image/jpeg",
    "bitrate" : 0,
    "duration" : 0,
    "title" : null,
    "properties" : null,
    "alternate" : [ {
      "href" : "https://i338.ntcdntempv3.com/data/images/37081/791604/025.jpg?data=net",
      "type" : "image/jpeg",
      "bitrate" : 0,
      "duration" : 0,
      "title" : null,
      "properties" : null,
      "alternate" : null
    } ]
  }, {
    "href" : "https://raw.githubusercontent.com/quetcccd/comic_storage7/main/IMAGE/IMAGE_3aa7cfaaae4b851a2a2ae1f4411dea9e_2c6acac7bf419c61f5f52672d84294b5_2766447c50624015ed7a84917b455694.jpg",
    "type" : "image/jpeg",
    "bitrate" : 0,
    "duration" : 0,
    "title" : null,
    "properties" : null,
    "alternate" : [ {
      "href" : "https://i338.ntcdntempv3.com/data/images/37081/791604/026.jpg?data=net",
      "type" : "image/jpeg",
      "bitrate" : 0,
      "duration" : 0,
      "title" : null,
      "properties" : null,
      "alternate" : null
    } ]
  }, {
    "href" : "https://raw.githubusercontent.com/quetcccd/comic_storage7/main/IMAGE/IMAGE_3aa7cfaaae4b851a2a2ae1f4411dea9e_2c6acac7bf419c61f5f52672d84294b5_3783294c20663af408971f1764c43450.jpg",
    "type" : "image/jpeg",
    "bitrate" : 0,
    "duration" : 0,
    "title" : null,
    "properties" : null,
    "alternate" : [ {
      "href" : "https://i338.ntcdntempv3.com/data/images/37081/791604/027.jpg?data=net",
      "type" : "image/jpeg",
      "bitrate" : 0,
      "duration" : 0,
      "title" : null,
      "properties" : null,
      "alternate" : null
    } ]
  }, {
    "href" : "https://raw.githubusercontent.com/quetcccd/comic_storage7/main/IMAGE/IMAGE_3aa7cfaaae4b851a2a2ae1f4411dea9e_2c6acac7bf419c61f5f52672d84294b5_57ad2bc77ede2f2d38999699aecc81b8.jpg",
    "type" : "image/jpeg",
    "bitrate" : 0,
    "duration" : 0,
    "title" : null,
    "properties" : null,
    "alternate" : [ {
      "href" : "https://i338.ntcdntempv3.com/data/images/37081/791604/028.jpg?data=net",
      "type" : "image/jpeg",
      "bitrate" : 0,
      "duration" : 0,
      "title" : null,
      "properties" : null,
      "alternate" : null
    } ]
  }, {
    "href" : "https://raw.githubusercontent.com/quetcccd/comic_storage7/main/IMAGE/IMAGE_3aa7cfaaae4b851a2a2ae1f4411dea9e_2c6acac7bf419c61f5f52672d84294b5_9b11589134fd559f0d6a55977417a3a7.jpg",
    "type" : "image/jpeg",
    "bitrate" : 0,
    "duration" : 0,
    "title" : null,
    "properties" : null,
    "alternate" : [ {
      "href" : "https://i338.ntcdntempv3.com/data/images/37081/791604/029.jpg?data=net",
      "type" : "image/jpeg",
      "bitrate" : 0,
      "duration" : 0,
      "title" : null,
      "properties" : null,
      "alternate" : null
    } ]
  }, {
    "href" : "https://raw.githubusercontent.com/quetcccd/comic_storage7/main/IMAGE/IMAGE_3aa7cfaaae4b851a2a2ae1f4411dea9e_2c6acac7bf419c61f5f52672d84294b5_7b243d9a18c44745c2a71ad896c60898.jpg",
    "type" : "image/jpeg",
    "bitrate" : 0,
    "duration" : 0,
    "title" : null,
    "properties" : null,
    "alternate" : [ {
      "href" : "https://i338.ntcdntempv3.com/data/images/37081/791604/030.jpg?data=net",
      "type" : "image/jpeg",
      "bitrate" : 0,
      "duration" : 0,
      "title" : null,
      "properties" : null,
      "alternate" : null
    } ]
  }, {
    "href" : "https://raw.githubusercontent.com/quetcccd/comic_storage7/main/IMAGE/IMAGE_3aa7cfaaae4b851a2a2ae1f4411dea9e_2c6acac7bf419c61f5f52672d84294b5_69a11b749118ddc0231f1c3153bc20a7.jpg",
    "type" : "image/jpeg",
    "bitrate" : 0,
    "duration" : 0,
    "title" : null,
    "properties" : null,
    "alternate" : [ {
      "href" : "https://i338.ntcdntempv3.com/data/images/37081/791604/031.jpg?data=net",
      "type" : "image/jpeg",
      "bitrate" : 0,
      "duration" : 0,
      "title" : null,
      "properties" : null,
      "alternate" : null
    } ]
  }, {
    "href" : "https://raw.githubusercontent.com/quetcccd/comic_storage7/main/IMAGE/IMAGE_3aa7cfaaae4b851a2a2ae1f4411dea9e_2c6acac7bf419c61f5f52672d84294b5_387ddc0159a12bd047e6f7e3fea1db9a.jpg",
    "type" : "image/jpeg",
    "bitrate" : 0,
    "duration" : 0,
    "title" : null,
    "properties" : null,
    "alternate" : [ {
      "href" : "https://i338.ntcdntempv3.com/data/images/37081/791604/032.jpg?data=net",
      "type" : "image/jpeg",
      "bitrate" : 0,
      "duration" : 0,
      "title" : null,
      "properties" : null,
      "alternate" : null
    } ]
  }, {
    "href" : "https://raw.githubusercontent.com/quetcccd/comic_storage7/main/IMAGE/IMAGE_3aa7cfaaae4b851a2a2ae1f4411dea9e_2c6acac7bf419c61f5f52672d84294b5_b4969ca109509b80833f5ceb55fb327e.jpg",
    "type" : "image/jpeg",
    "bitrate" : 0,
    "duration" : 0,
    "title" : null,
    "properties" : null,
    "alternate" : [ {
      "href" : "https://i338.ntcdntempv3.com/data/images/37081/791604/033.jpg?data=net",
      "type" : "image/jpeg",
      "bitrate" : 0,
      "duration" : 0,
      "title" : null,
      "properties" : null,
      "alternate" : null
    } ]
  } ],
  "toc" : null,
  "@context" : "https://readium.org/webpub-manifest/context.jsonld"
}