{
  "metadata" : {
    "identifier" : "https://nghetruyenma.net/sut-ho-cau-nhai.html",
    "title" : "Sụt Hố Cầu Nhái",
    "subtitle" : "N/A",
    "author" : {
      "name" : "Lệ Giang",
      "sortAs" : ""
    },
    "narrator" : "N/A",
    "language" : "vi",
    "description" : "N/A",
    "publisher" : "N/A",
    "subject" : null,
    "modified" : null,
    "published" : "2023-06-27",
    "duration" : 4648,
    "abridged" : false,
    "conformsTo" : null,
    "numberOfPages" : null,
    "readingProgression" : null,
    "belongsTo" : null,
    "presentation" : null,
    "@type" : "http://schema.org/Audiobook",
    "schema:license" : "https://creativecommons.org/publicdomain/zero/1.0/"
  },
  "links" : [ {
    "rel" : "self",
    "href" : "https://raw.githubusercontent.com/vietduyhuynh90s/book_storage_two7/main/EPUB/EPUB_d1348acd151b6e129ddcbb29dbd7aca0.json",
    "type" : "application/audiobook+json"
  }, {
    "rel" : "cover",
    "href" : "https://raw.githubusercontent.com/vietduyhuynh90s/book_storage_two7/main/IMAGE/IMAGE_d1348acd151b6e129ddcbb29dbd7aca0.jpg",
    "type" : "image/jpeg",
    "height" : 300,
    "width" : 300
  } ],
  "readingOrder" : [ {
    "href" : "https://archive.org/download/sut-ho-cau-nhai/sut-ho-cau-nhai.mp3",
    "type" : "audio/mpeg",
    "bitrate" : 128,
    "duration" : 4648,
    "title" : "sut-ho-cau-nhai",
    "properties" : null,
    "alternate" : null
  } ],
  "toc" : [ {
    "href" : "https://archive.org/download/sut-ho-cau-nhai/sut-ho-cau-nhai.mp3",
    "title" : "sut-ho-cau-nhai",
    "children" : [ ]
  } ],
  "@context" : "https://readium.org/webpub-manifest/context.jsonld"
}