{
  "metadata" : {
    "identifier" : "https://www.dtv-ebook.com/than-den-hoang-hau_13546.html",
    "title" : "Than Đen Hoàng Hậu",
    "subtitle" : "N/A",
    "author" : {
      "name" : "Nguyên Viện",
      "sortAs" : ""
    },
    "narrator" : "N/A",
    "language" : "vi",
    "description" : "<p>N/A</p>",
    "publisher" : "N/A",
    "subject" : null,
    "modified" : null,
    "published" : "2023-05-09",
    "duration" : 15004,
    "abridged" : false,
    "conformsTo" : null,
    "numberOfPages" : null,
    "readingProgression" : null,
    "belongsTo" : null,
    "presentation" : null,
    "@type" : "http://schema.org/Audiobook",
    "schema:license" : "https://creativecommons.org/publicdomain/zero/1.0/"
  },
  "links" : [ {
    "rel" : "self",
    "href" : "https://raw.githubusercontent.com/vietduyhuynh90s/book_storage_two7/main/EPUB/EPUB_6f4e925ca2c613d897542ec5a4724587.json",
    "type" : "application/audiobook+json"
  }, {
    "rel" : "cover",
    "href" : "https://raw.githubusercontent.com/vietduyhuynh90s/book_storage_two7/main/IMAGE/IMAGE_6f4e925ca2c613d897542ec5a4724587.jpg",
    "type" : "image/jpeg",
    "height" : 300,
    "width" : 300
  } ],
  "readingOrder" : [ {
    "href" : "https://archive.org/download/than-den-hoang-hau/1.mp3",
    "type" : "audio/mpeg",
    "bitrate" : 128,
    "duration" : 3717,
    "title" : "TRUYỆN NGÔN TÌNH SẮC XUYÊN KHÔNG NGẮN NHƯNG HAY - MC BẢO ANH",
    "properties" : null,
    "alternate" : null
  }, {
    "href" : "https://archive.org/download/than-den-hoang-hau/2.mp3",
    "type" : "audio/mpeg",
    "bitrate" : 128,
    "duration" : 3729,
    "title" : "TRUYỆN NGÔN TÌNH SẮC XUYÊN KHÔNG NGẮN NHƯNG HAY - MC BẢO ANH",
    "properties" : null,
    "alternate" : null
  }, {
    "href" : "https://archive.org/download/than-den-hoang-hau/3.mp3",
    "type" : "audio/mpeg",
    "bitrate" : 128,
    "duration" : 3736,
    "title" : "TRUYỆN NGÔN TÌNH SẮC XUYÊN KHÔNG NGẮN NHƯNG HAY - MC BẢO ANH",
    "properties" : null,
    "alternate" : null
  }, {
    "href" : "https://archive.org/download/than-den-hoang-hau/4.mp3",
    "type" : "audio/mpeg",
    "bitrate" : 128,
    "duration" : 3822,
    "title" : "TRUYỆN NGÔN TÌNH SẮC XUYÊN KHÔNG NGẮN NHƯNG HAY - MC BẢO ANH",
    "properties" : null,
    "alternate" : null
  } ],
  "toc" : [ {
    "href" : "https://archive.org/download/than-den-hoang-hau/1.mp3",
    "title" : "TRUYỆN NGÔN TÌNH SẮC XUYÊN KHÔNG NGẮN NHƯNG HAY - MC BẢO ANH",
    "children" : [ ]
  }, {
    "href" : "https://archive.org/download/than-den-hoang-hau/2.mp3",
    "title" : "TRUYỆN NGÔN TÌNH SẮC XUYÊN KHÔNG NGẮN NHƯNG HAY - MC BẢO ANH",
    "children" : [ ]
  }, {
    "href" : "https://archive.org/download/than-den-hoang-hau/3.mp3",
    "title" : "TRUYỆN NGÔN TÌNH SẮC XUYÊN KHÔNG NGẮN NHƯNG HAY - MC BẢO ANH",
    "children" : [ ]
  }, {
    "href" : "https://archive.org/download/than-den-hoang-hau/4.mp3",
    "title" : "TRUYỆN NGÔN TÌNH SẮC XUYÊN KHÔNG NGẮN NHƯNG HAY - MC BẢO ANH",
    "children" : [ ]
  } ],
  "@context" : "https://readium.org/webpub-manifest/context.jsonld"
}