{
  "metadata" : {
    "identifier" : "https://nghetruyenma.net/oan-hon-ong-tu.html",
    "title" : "Oán Hồn Ông Tư",
    "subtitle" : "N/A",
    "author" : {
      "name" : "Khả Hân",
      "sortAs" : ""
    },
    "narrator" : "N/A",
    "language" : "vi",
    "description" : "N/A",
    "publisher" : "N/A",
    "subject" : null,
    "modified" : null,
    "published" : "2023-06-26",
    "duration" : 0,
    "abridged" : false,
    "conformsTo" : null,
    "numberOfPages" : null,
    "readingProgression" : null,
    "belongsTo" : null,
    "presentation" : null,
    "@type" : "http://schema.org/Audiobook",
    "schema:license" : "https://creativecommons.org/publicdomain/zero/1.0/"
  },
  "links" : [ {
    "rel" : "self",
    "href" : "https://raw.githubusercontent.com/vietduyhuynh90s/book_storage_two7/main/EPUB/EPUB_a53f59ac987e8bb005f00309a18ab242.json",
    "type" : "application/audiobook+json"
  }, {
    "rel" : "cover",
    "href" : "https://raw.githubusercontent.com/vietduyhuynh90s/book_storage_two7/main/IMAGE/IMAGE_a53f59ac987e8bb005f00309a18ab242.jpg",
    "type" : "image/jpeg",
    "height" : 300,
    "width" : 300
  } ],
  "readingOrder" : [ {
    "href" : "https://ia801508.us.archive.org/34/items/ong-tu/ong-tu.mp3",
    "type" : "audio/mpeg",
    "bitrate" : 128,
    "duration" : 0,
    "title" : "Oán hồn ông tư",
    "properties" : null,
    "alternate" : null
  } ],
  "toc" : [ {
    "href" : "https://ia801508.us.archive.org/34/items/ong-tu/ong-tu.mp3",
    "title" : "Oán hồn ông tư",
    "children" : [ ]
  } ],
  "@context" : "https://readium.org/webpub-manifest/context.jsonld"
}