{
  "metadata" : {
    "identifier" : "https://nhattruyenz.com/truyen-tranh/xay-dung-dia-nguc",
    "title" : "Xây Dựng Địa Ngục",
    "subtitle" : null,
    "author" : null,
    "narrator" : null,
    "language" : "vi",
    "description" : null,
    "publisher" : "N/A",
    "subject" : null,
    "modified" : null,
    "published" : "2023-04-29",
    "duration" : 0,
    "abridged" : false,
    "conformsTo" : "https://readium.org/webpub-manifest/profiles/divina",
    "numberOfPages" : 4,
    "readingProgression" : "ttb",
    "belongsTo" : null,
    "presentation" : {
      "fit" : "width",
      "overflow" : "scrolled",
      "continuous" : true
    },
    "@type" : null,
    "schema:license" : null
  },
  "links" : [ {
    "rel" : "self",
    "href" : "https://raw.githubusercontent.com/thuvienonline40/book_storage_collection/main/comic_manifest.json",
    "type" : "application/divina+json"
  } ],
  "readingOrder" : [ {
    "href" : "https://i2.wp.com/img.abctruyen.xyz/uploads/18653/chuong-2/1.jpg",
    "type" : "image/jpeg",
    "bitrate" : 0,
    "duration" : 0,
    "title" : null,
    "properties" : null
  }, {
    "href" : "https://i2.wp.com/img.abctruyen.xyz/uploads/18653/chuong-2/2.jpg",
    "type" : "image/jpeg",
    "bitrate" : 0,
    "duration" : 0,
    "title" : null,
    "properties" : null
  }, {
    "href" : "https://i2.wp.com/img.abctruyen.xyz/uploads/18653/chuong-2/3.jpg",
    "type" : "image/jpeg",
    "bitrate" : 0,
    "duration" : 0,
    "title" : null,
    "properties" : null
  }, {
    "href" : "https://i2.wp.com/img.abctruyen.xyz/uploads/18653/chuong-2/4.jpg",
    "type" : "image/jpeg",
    "bitrate" : 0,
    "duration" : 0,
    "title" : null,
    "properties" : null
  }, {
    "href" : "https://i2.wp.com/img.abctruyen.xyz/uploads/18653/chuong-2/5.jpg",
    "type" : "image/jpeg",
    "bitrate" : 0,
    "duration" : 0,
    "title" : null,
    "properties" : null
  }, {
    "href" : "https://i2.wp.com/img.abctruyen.xyz/uploads/18653/chuong-2/6.jpg",
    "type" : "image/jpeg",
    "bitrate" : 0,
    "duration" : 0,
    "title" : null,
    "properties" : null
  }, {
    "href" : "https://i2.wp.com/img.abctruyen.xyz/uploads/18653/chuong-2/7.jpg",
    "type" : "image/jpeg",
    "bitrate" : 0,
    "duration" : 0,
    "title" : null,
    "properties" : null
  }, {
    "href" : "https://i2.wp.com/img.abctruyen.xyz/uploads/18653/chuong-2/8.jpg",
    "type" : "image/jpeg",
    "bitrate" : 0,
    "duration" : 0,
    "title" : null,
    "properties" : null
  }, {
    "href" : "https://i2.wp.com/img.abctruyen.xyz/uploads/18653/chuong-2/9.jpg",
    "type" : "image/jpeg",
    "bitrate" : 0,
    "duration" : 0,
    "title" : null,
    "properties" : null
  }, {
    "href" : "https://i2.wp.com/img.abctruyen.xyz/uploads/18653/chuong-2/10.jpg",
    "type" : "image/jpeg",
    "bitrate" : 0,
    "duration" : 0,
    "title" : null,
    "properties" : null
  }, {
    "href" : "https://i2.wp.com/img.abctruyen.xyz/uploads/18653/chuong-2/11.jpg",
    "type" : "image/jpeg",
    "bitrate" : 0,
    "duration" : 0,
    "title" : null,
    "properties" : null
  }, {
    "href" : "https://i2.wp.com/img.abctruyen.xyz/uploads/18653/chuong-2/12.jpg",
    "type" : "image/jpeg",
    "bitrate" : 0,
    "duration" : 0,
    "title" : null,
    "properties" : null
  }, {
    "href" : "https://i2.wp.com/img.abctruyen.xyz/uploads/18653/chuong-2/13.jpg",
    "type" : "image/jpeg",
    "bitrate" : 0,
    "duration" : 0,
    "title" : null,
    "properties" : null
  }, {
    "href" : "https://i2.wp.com/img.abctruyen.xyz/uploads/18653/chuong-2/14.jpg",
    "type" : "image/jpeg",
    "bitrate" : 0,
    "duration" : 0,
    "title" : null,
    "properties" : null
  }, {
    "href" : "https://i2.wp.com/img.abctruyen.xyz/uploads/18653/chuong-2/15.jpg",
    "type" : "image/jpeg",
    "bitrate" : 0,
    "duration" : 0,
    "title" : null,
    "properties" : null
  }, {
    "href" : "https://i2.wp.com/img.abctruyen.xyz/uploads/18653/chuong-2/16.jpg",
    "type" : "image/jpeg",
    "bitrate" : 0,
    "duration" : 0,
    "title" : null,
    "properties" : null
  }, {
    "href" : "https://i2.wp.com/img.abctruyen.xyz/uploads/18653/chuong-2/17.jpg",
    "type" : "image/jpeg",
    "bitrate" : 0,
    "duration" : 0,
    "title" : null,
    "properties" : null
  }, {
    "href" : "https://i2.wp.com/img.abctruyen.xyz/uploads/18653/chuong-2/18.jpg",
    "type" : "image/jpeg",
    "bitrate" : 0,
    "duration" : 0,
    "title" : null,
    "properties" : null
  }, {
    "href" : "https://i2.wp.com/img.abctruyen.xyz/uploads/18653/chuong-2/19.jpg",
    "type" : "image/jpeg",
    "bitrate" : 0,
    "duration" : 0,
    "title" : null,
    "properties" : null
  }, {
    "href" : "https://i2.wp.com/img.abctruyen.xyz/uploads/18653/chuong-2/20.jpg",
    "type" : "image/jpeg",
    "bitrate" : 0,
    "duration" : 0,
    "title" : null,
    "properties" : null
  }, {
    "href" : "https://i2.wp.com/img.abctruyen.xyz/uploads/18653/chuong-2/21.jpg",
    "type" : "image/jpeg",
    "bitrate" : 0,
    "duration" : 0,
    "title" : null,
    "properties" : null
  }, {
    "href" : "https://i2.wp.com/img.abctruyen.xyz/uploads/18653/chuong-2/22.jpg",
    "type" : "image/jpeg",
    "bitrate" : 0,
    "duration" : 0,
    "title" : null,
    "properties" : null
  }, {
    "href" : "https://i2.wp.com/img.abctruyen.xyz/uploads/18653/chuong-2/23.jpg",
    "type" : "image/jpeg",
    "bitrate" : 0,
    "duration" : 0,
    "title" : null,
    "properties" : null
  }, {
    "href" : "https://i2.wp.com/img.abctruyen.xyz/uploads/18653/chuong-2/24.jpg",
    "type" : "image/jpeg",
    "bitrate" : 0,
    "duration" : 0,
    "title" : null,
    "properties" : null
  }, {
    "href" : "https://i2.wp.com/img.abctruyen.xyz/uploads/18653/chuong-2/25.jpg",
    "type" : "image/jpeg",
    "bitrate" : 0,
    "duration" : 0,
    "title" : null,
    "properties" : null
  }, {
    "href" : "https://i2.wp.com/img.abctruyen.xyz/uploads/18653/chuong-2/26.jpg",
    "type" : "image/jpeg",
    "bitrate" : 0,
    "duration" : 0,
    "title" : null,
    "properties" : null
  }, {
    "href" : "https://i2.wp.com/img.abctruyen.xyz/uploads/18653/chuong-2/27.jpg",
    "type" : "image/jpeg",
    "bitrate" : 0,
    "duration" : 0,
    "title" : null,
    "properties" : null
  }, {
    "href" : "https://i2.wp.com/img.abctruyen.xyz/uploads/18653/chuong-2/28.jpg",
    "type" : "image/jpeg",
    "bitrate" : 0,
    "duration" : 0,
    "title" : null,
    "properties" : null
  }, {
    "href" : "https://i2.wp.com/img.abctruyen.xyz/uploads/18653/chuong-2/29.jpg",
    "type" : "image/jpeg",
    "bitrate" : 0,
    "duration" : 0,
    "title" : null,
    "properties" : null
  }, {
    "href" : "https://i2.wp.com/img.abctruyen.xyz/uploads/18653/chuong-2/30.jpg",
    "type" : "image/jpeg",
    "bitrate" : 0,
    "duration" : 0,
    "title" : null,
    "properties" : null
  }, {
    "href" : "https://i2.wp.com/img.abctruyen.xyz/uploads/18653/chuong-2/31.jpg",
    "type" : "image/jpeg",
    "bitrate" : 0,
    "duration" : 0,
    "title" : null,
    "properties" : null
  }, {
    "href" : "https://i2.wp.com/img.abctruyen.xyz/uploads/18653/chuong-2/32.jpg",
    "type" : "image/jpeg",
    "bitrate" : 0,
    "duration" : 0,
    "title" : null,
    "properties" : null
  }, {
    "href" : "https://i2.wp.com/img.abctruyen.xyz/uploads/18653/chuong-2/33.jpg",
    "type" : "image/jpeg",
    "bitrate" : 0,
    "duration" : 0,
    "title" : null,
    "properties" : null
  }, {
    "href" : "https://i2.wp.com/img.abctruyen.xyz/uploads/18653/chuong-2/34.jpg",
    "type" : "image/jpeg",
    "bitrate" : 0,
    "duration" : 0,
    "title" : null,
    "properties" : null
  }, {
    "href" : "https://i2.wp.com/img.abctruyen.xyz/uploads/18653/chuong-2/35.jpg",
    "type" : "image/jpeg",
    "bitrate" : 0,
    "duration" : 0,
    "title" : null,
    "properties" : null
  }, {
    "href" : "https://i2.wp.com/img.abctruyen.xyz/uploads/18653/chuong-2/36.jpg",
    "type" : "image/jpeg",
    "bitrate" : 0,
    "duration" : 0,
    "title" : null,
    "properties" : null
  }, {
    "href" : "https://i2.wp.com/img.abctruyen.xyz/uploads/18653/chuong-2/37.jpg",
    "type" : "image/jpeg",
    "bitrate" : 0,
    "duration" : 0,
    "title" : null,
    "properties" : null
  }, {
    "href" : "https://i2.wp.com/img.abctruyen.xyz/uploads/18653/chuong-2/38.jpg",
    "type" : "image/jpeg",
    "bitrate" : 0,
    "duration" : 0,
    "title" : null,
    "properties" : null
  }, {
    "href" : "https://i2.wp.com/img.abctruyen.xyz/uploads/18653/chuong-2/39.jpg",
    "type" : "image/jpeg",
    "bitrate" : 0,
    "duration" : 0,
    "title" : null,
    "properties" : null
  }, {
    "href" : "https://i2.wp.com/img.abctruyen.xyz/uploads/18653/chuong-2/40.jpg",
    "type" : "image/jpeg",
    "bitrate" : 0,
    "duration" : 0,
    "title" : null,
    "properties" : null
  }, {
    "href" : "https://i2.wp.com/img.abctruyen.xyz/uploads/18653/chuong-2/41.jpg",
    "type" : "image/jpeg",
    "bitrate" : 0,
    "duration" : 0,
    "title" : null,
    "properties" : null
  }, {
    "href" : "https://i2.wp.com/img.abctruyen.xyz/uploads/18653/chuong-2/42.jpg",
    "type" : "image/jpeg",
    "bitrate" : 0,
    "duration" : 0,
    "title" : null,
    "properties" : null
  }, {
    "href" : "https://i2.wp.com/img.abctruyen.xyz/uploads/18653/chuong-2/43.jpg",
    "type" : "image/jpeg",
    "bitrate" : 0,
    "duration" : 0,
    "title" : null,
    "properties" : null
  }, {
    "href" : "https://i2.wp.com/img.abctruyen.xyz/uploads/18653/chuong-2/44.jpg",
    "type" : "image/jpeg",
    "bitrate" : 0,
    "duration" : 0,
    "title" : null,
    "properties" : null
  }, {
    "href" : "https://i2.wp.com/img.abctruyen.xyz/uploads/18653/chuong-2/45.jpg",
    "type" : "image/jpeg",
    "bitrate" : 0,
    "duration" : 0,
    "title" : null,
    "properties" : null
  }, {
    "href" : "https://i2.wp.com/img.abctruyen.xyz/uploads/18653/chuong-2/46.jpg",
    "type" : "image/jpeg",
    "bitrate" : 0,
    "duration" : 0,
    "title" : null,
    "properties" : null
  }, {
    "href" : "https://i2.wp.com/img.abctruyen.xyz/uploads/18653/chuong-2/47.jpg",
    "type" : "image/jpeg",
    "bitrate" : 0,
    "duration" : 0,
    "title" : null,
    "properties" : null
  }, {
    "href" : "https://i2.wp.com/img.abctruyen.xyz/uploads/18653/chuong-2/48.jpg",
    "type" : "image/jpeg",
    "bitrate" : 0,
    "duration" : 0,
    "title" : null,
    "properties" : null
  }, {
    "href" : "https://i2.wp.com/img.abctruyen.xyz/uploads/18653/chuong-2/49.jpg",
    "type" : "image/jpeg",
    "bitrate" : 0,
    "duration" : 0,
    "title" : null,
    "properties" : null
  }, {
    "href" : "https://i2.wp.com/img.abctruyen.xyz/uploads/18653/chuong-2/50.jpg",
    "type" : "image/jpeg",
    "bitrate" : 0,
    "duration" : 0,
    "title" : null,
    "properties" : null
  }, {
    "href" : "https://i2.wp.com/img.abctruyen.xyz/uploads/18653/chuong-2/51.jpg",
    "type" : "image/jpeg",
    "bitrate" : 0,
    "duration" : 0,
    "title" : null,
    "properties" : null
  }, {
    "href" : "https://i2.wp.com/img.abctruyen.xyz/uploads/18653/chuong-2/52.jpg",
    "type" : "image/jpeg",
    "bitrate" : 0,
    "duration" : 0,
    "title" : null,
    "properties" : null
  }, {
    "href" : "https://i2.wp.com/img.abctruyen.xyz/uploads/18653/chuong-2/53.jpg",
    "type" : "image/jpeg",
    "bitrate" : 0,
    "duration" : 0,
    "title" : null,
    "properties" : null
  }, {
    "href" : "https://i2.wp.com/img.abctruyen.xyz/uploads/18653/chuong-2/54.jpg",
    "type" : "image/jpeg",
    "bitrate" : 0,
    "duration" : 0,
    "title" : null,
    "properties" : null
  }, {
    "href" : "https://i2.wp.com/img.abctruyen.xyz/uploads/18653/chuong-2/55.jpg",
    "type" : "image/jpeg",
    "bitrate" : 0,
    "duration" : 0,
    "title" : null,
    "properties" : null
  }, {
    "href" : "https://i2.wp.com/img.abctruyen.xyz/uploads/18653/chuong-2/56.jpg",
    "type" : "image/jpeg",
    "bitrate" : 0,
    "duration" : 0,
    "title" : null,
    "properties" : null
  }, {
    "href" : "https://i2.wp.com/img.abctruyen.xyz/uploads/18653/chuong-2/57.jpg",
    "type" : "image/jpeg",
    "bitrate" : 0,
    "duration" : 0,
    "title" : null,
    "properties" : null
  }, {
    "href" : "https://i2.wp.com/img.abctruyen.xyz/uploads/18653/chuong-2/58.jpg",
    "type" : "image/jpeg",
    "bitrate" : 0,
    "duration" : 0,
    "title" : null,
    "properties" : null
  }, {
    "href" : "https://i2.wp.com/img.abctruyen.xyz/uploads/18653/chuong-2/59.jpg",
    "type" : "image/jpeg",
    "bitrate" : 0,
    "duration" : 0,
    "title" : null,
    "properties" : null
  }, {
    "href" : "https://i2.wp.com/img.abctruyen.xyz/uploads/18653/chuong-2/60.jpg",
    "type" : "image/jpeg",
    "bitrate" : 0,
    "duration" : 0,
    "title" : null,
    "properties" : null
  }, {
    "href" : "https://i2.wp.com/img.abctruyen.xyz/uploads/18653/chuong-2/61.jpg",
    "type" : "image/jpeg",
    "bitrate" : 0,
    "duration" : 0,
    "title" : null,
    "properties" : null
  }, {
    "href" : "https://i2.wp.com/img.abctruyen.xyz/uploads/18653/chuong-2/62.jpg",
    "type" : "image/jpeg",
    "bitrate" : 0,
    "duration" : 0,
    "title" : null,
    "properties" : null
  }, {
    "href" : "https://i2.wp.com/img.abctruyen.xyz/uploads/18653/chuong-2/63.jpg",
    "type" : "image/jpeg",
    "bitrate" : 0,
    "duration" : 0,
    "title" : null,
    "properties" : null
  }, {
    "href" : "https://i2.wp.com/img.abctruyen.xyz/uploads/18653/chuong-2/64.jpg",
    "type" : "image/jpeg",
    "bitrate" : 0,
    "duration" : 0,
    "title" : null,
    "properties" : null
  }, {
    "href" : "https://i2.wp.com/img.abctruyen.xyz/uploads/18653/chuong-2/65.jpg",
    "type" : "image/jpeg",
    "bitrate" : 0,
    "duration" : 0,
    "title" : null,
    "properties" : null
  }, {
    "href" : "https://i2.wp.com/img.abctruyen.xyz/uploads/18653/chuong-2/66.jpg",
    "type" : "image/jpeg",
    "bitrate" : 0,
    "duration" : 0,
    "title" : null,
    "properties" : null
  }, {
    "href" : "https://i2.wp.com/img.abctruyen.xyz/uploads/18653/chuong-2/67.jpg",
    "type" : "image/jpeg",
    "bitrate" : 0,
    "duration" : 0,
    "title" : null,
    "properties" : null
  }, {
    "href" : "https://i2.wp.com/img.abctruyen.xyz/uploads/18653/chuong-2/68.jpg",
    "type" : "image/jpeg",
    "bitrate" : 0,
    "duration" : 0,
    "title" : null,
    "properties" : null
  }, {
    "href" : "https://i2.wp.com/img.abctruyen.xyz/uploads/18653/chuong-2/69.jpg",
    "type" : "image/jpeg",
    "bitrate" : 0,
    "duration" : 0,
    "title" : null,
    "properties" : null
  }, {
    "href" : "https://i2.wp.com/img.abctruyen.xyz/uploads/18653/chuong-2/70.jpg",
    "type" : "image/jpeg",
    "bitrate" : 0,
    "duration" : 0,
    "title" : null,
    "properties" : null
  }, {
    "href" : "https://i2.wp.com/img.abctruyen.xyz/uploads/18653/chuong-2/71.jpg",
    "type" : "image/jpeg",
    "bitrate" : 0,
    "duration" : 0,
    "title" : null,
    "properties" : null
  }, {
    "href" : "https://i2.wp.com/img.abctruyen.xyz/uploads/18653/chuong-2/72.jpg",
    "type" : "image/jpeg",
    "bitrate" : 0,
    "duration" : 0,
    "title" : null,
    "properties" : null
  }, {
    "href" : "https://i2.wp.com/img.abctruyen.xyz/uploads/18653/chuong-2/73.jpg",
    "type" : "image/jpeg",
    "bitrate" : 0,
    "duration" : 0,
    "title" : null,
    "properties" : null
  }, {
    "href" : "https://i2.wp.com/img.abctruyen.xyz/uploads/18653/chuong-2/74.jpg",
    "type" : "image/jpeg",
    "bitrate" : 0,
    "duration" : 0,
    "title" : null,
    "properties" : null
  }, {
    "href" : "https://i2.wp.com/img.abctruyen.xyz/uploads/18653/chuong-2/75.jpg",
    "type" : "image/jpeg",
    "bitrate" : 0,
    "duration" : 0,
    "title" : null,
    "properties" : null
  }, {
    "href" : "https://i2.wp.com/img.abctruyen.xyz/uploads/18653/chuong-2/76.jpg",
    "type" : "image/jpeg",
    "bitrate" : 0,
    "duration" : 0,
    "title" : null,
    "properties" : null
  }, {
    "href" : "https://i2.wp.com/img.abctruyen.xyz/uploads/18653/chuong-2/77.jpg",
    "type" : "image/jpeg",
    "bitrate" : 0,
    "duration" : 0,
    "title" : null,
    "properties" : null
  }, {
    "href" : "https://i2.wp.com/img.abctruyen.xyz/uploads/18653/chuong-2/78.jpg",
    "type" : "image/jpeg",
    "bitrate" : 0,
    "duration" : 0,
    "title" : null,
    "properties" : null
  }, {
    "href" : "https://i2.wp.com/img.abctruyen.xyz/uploads/18653/chuong-2/79.jpg",
    "type" : "image/jpeg",
    "bitrate" : 0,
    "duration" : 0,
    "title" : null,
    "properties" : null
  }, {
    "href" : "https://i2.wp.com/img.abctruyen.xyz/uploads/18653/chuong-2/80.jpg",
    "type" : "image/jpeg",
    "bitrate" : 0,
    "duration" : 0,
    "title" : null,
    "properties" : null
  }, {
    "href" : "https://i2.wp.com/img.abctruyen.xyz/uploads/18653/chuong-2/81.jpg",
    "type" : "image/jpeg",
    "bitrate" : 0,
    "duration" : 0,
    "title" : null,
    "properties" : null
  }, {
    "href" : "https://i2.wp.com/img.abctruyen.xyz/uploads/18653/chuong-2/82.jpg",
    "type" : "image/jpeg",
    "bitrate" : 0,
    "duration" : 0,
    "title" : null,
    "properties" : null
  }, {
    "href" : "https://i2.wp.com/img.abctruyen.xyz/uploads/18653/chuong-2/83.jpg",
    "type" : "image/jpeg",
    "bitrate" : 0,
    "duration" : 0,
    "title" : null,
    "properties" : null
  }, {
    "href" : "https://i2.wp.com/img.abctruyen.xyz/uploads/18653/chuong-2/84.jpg",
    "type" : "image/jpeg",
    "bitrate" : 0,
    "duration" : 0,
    "title" : null,
    "properties" : null
  }, {
    "href" : "https://i2.wp.com/img.abctruyen.xyz/uploads/18653/chuong-2/85.jpg",
    "type" : "image/jpeg",
    "bitrate" : 0,
    "duration" : 0,
    "title" : null,
    "properties" : null
  }, {
    "href" : "https://i2.wp.com/img.abctruyen.xyz/uploads/18653/chuong-2/86.jpg",
    "type" : "image/jpeg",
    "bitrate" : 0,
    "duration" : 0,
    "title" : null,
    "properties" : null
  }, {
    "href" : "https://i2.wp.com/img.abctruyen.xyz/uploads/18653/chuong-2/87.jpg",
    "type" : "image/jpeg",
    "bitrate" : 0,
    "duration" : 0,
    "title" : null,
    "properties" : null
  }, {
    "href" : "https://i2.wp.com/img.abctruyen.xyz/uploads/18653/chuong-2/88.jpg",
    "type" : "image/jpeg",
    "bitrate" : 0,
    "duration" : 0,
    "title" : null,
    "properties" : null
  }, {
    "href" : "https://i2.wp.com/img.abctruyen.xyz/uploads/18653/chuong-2/89.jpg",
    "type" : "image/jpeg",
    "bitrate" : 0,
    "duration" : 0,
    "title" : null,
    "properties" : null
  }, {
    "href" : "https://i2.wp.com/img.abctruyen.xyz/uploads/18653/chuong-2/90.jpg",
    "type" : "image/jpeg",
    "bitrate" : 0,
    "duration" : 0,
    "title" : null,
    "properties" : null
  }, {
    "href" : "https://i2.wp.com/img.abctruyen.xyz/uploads/18653/chuong-2/91.jpg",
    "type" : "image/jpeg",
    "bitrate" : 0,
    "duration" : 0,
    "title" : null,
    "properties" : null
  }, {
    "href" : "https://i2.wp.com/img.abctruyen.xyz/uploads/18653/chuong-2/92.jpg",
    "type" : "image/jpeg",
    "bitrate" : 0,
    "duration" : 0,
    "title" : null,
    "properties" : null
  }, {
    "href" : "https://i2.wp.com/img.abctruyen.xyz/uploads/18653/chuong-2/93.jpg",
    "type" : "image/jpeg",
    "bitrate" : 0,
    "duration" : 0,
    "title" : null,
    "properties" : null
  }, {
    "href" : "https://i2.wp.com/img.abctruyen.xyz/uploads/18653/chuong-2/94.jpg",
    "type" : "image/jpeg",
    "bitrate" : 0,
    "duration" : 0,
    "title" : null,
    "properties" : null
  }, {
    "href" : "https://i2.wp.com/img.abctruyen.xyz/uploads/18653/chuong-2/95.jpg",
    "type" : "image/jpeg",
    "bitrate" : 0,
    "duration" : 0,
    "title" : null,
    "properties" : null
  }, {
    "href" : "https://i2.wp.com/img.abctruyen.xyz/uploads/18653/chuong-2/96.jpg",
    "type" : "image/jpeg",
    "bitrate" : 0,
    "duration" : 0,
    "title" : null,
    "properties" : null
  }, {
    "href" : "https://i2.wp.com/img.abctruyen.xyz/uploads/18653/chuong-2/97.jpg",
    "type" : "image/jpeg",
    "bitrate" : 0,
    "duration" : 0,
    "title" : null,
    "properties" : null
  }, {
    "href" : "https://i2.wp.com/img.abctruyen.xyz/uploads/18653/chuong-2/98.jpg",
    "type" : "image/jpeg",
    "bitrate" : 0,
    "duration" : 0,
    "title" : null,
    "properties" : null
  }, {
    "href" : "https://i2.wp.com/img.abctruyen.xyz/uploads/18653/chuong-2/99.jpg",
    "type" : "image/jpeg",
    "bitrate" : 0,
    "duration" : 0,
    "title" : null,
    "properties" : null
  }, {
    "href" : "https://i2.wp.com/img.abctruyen.xyz/uploads/18653/chuong-2/100.jpg",
    "type" : "image/jpeg",
    "bitrate" : 0,
    "duration" : 0,
    "title" : null,
    "properties" : null
  }, {
    "href" : "https://i2.wp.com/img.abctruyen.xyz/uploads/18653/chuong-2/101.jpg",
    "type" : "image/jpeg",
    "bitrate" : 0,
    "duration" : 0,
    "title" : null,
    "properties" : null
  }, {
    "href" : "https://i2.wp.com/img.abctruyen.xyz/uploads/18653/chuong-2/102.jpg",
    "type" : "image/jpeg",
    "bitrate" : 0,
    "duration" : 0,
    "title" : null,
    "properties" : null
  }, {
    "href" : "https://i2.wp.com/img.abctruyen.xyz/uploads/18653/chuong-2/103.jpg",
    "type" : "image/jpeg",
    "bitrate" : 0,
    "duration" : 0,
    "title" : null,
    "properties" : null
  }, {
    "href" : "https://i2.wp.com/img.abctruyen.xyz/uploads/18653/chuong-2/104.jpg",
    "type" : "image/jpeg",
    "bitrate" : 0,
    "duration" : 0,
    "title" : null,
    "properties" : null
  }, {
    "href" : "https://i2.wp.com/img.abctruyen.xyz/uploads/18653/chuong-2/105.jpg",
    "type" : "image/jpeg",
    "bitrate" : 0,
    "duration" : 0,
    "title" : null,
    "properties" : null
  }, {
    "href" : "https://i2.wp.com/img.abctruyen.xyz/uploads/18653/chuong-2/106.jpg",
    "type" : "image/jpeg",
    "bitrate" : 0,
    "duration" : 0,
    "title" : null,
    "properties" : null
  }, {
    "href" : "https://i2.wp.com/img.abctruyen.xyz/uploads/18653/chuong-2/107.jpg",
    "type" : "image/jpeg",
    "bitrate" : 0,
    "duration" : 0,
    "title" : null,
    "properties" : null
  }, {
    "href" : "https://i2.wp.com/img.abctruyen.xyz/uploads/18653/chuong-2/108.jpg",
    "type" : "image/jpeg",
    "bitrate" : 0,
    "duration" : 0,
    "title" : null,
    "properties" : null
  }, {
    "href" : "https://i2.wp.com/img.abctruyen.xyz/uploads/18653/chuong-2/109.jpg",
    "type" : "image/jpeg",
    "bitrate" : 0,
    "duration" : 0,
    "title" : null,
    "properties" : null
  }, {
    "href" : "https://i2.wp.com/img.abctruyen.xyz/uploads/18653/chuong-2/110.jpg",
    "type" : "image/jpeg",
    "bitrate" : 0,
    "duration" : 0,
    "title" : null,
    "properties" : null
  }, {
    "href" : "https://i2.wp.com/img.abctruyen.xyz/uploads/18653/chuong-2/111.jpg",
    "type" : "image/jpeg",
    "bitrate" : 0,
    "duration" : 0,
    "title" : null,
    "properties" : null
  }, {
    "href" : "https://i2.wp.com/img.abctruyen.xyz/uploads/18653/chuong-2/112.jpg",
    "type" : "image/jpeg",
    "bitrate" : 0,
    "duration" : 0,
    "title" : null,
    "properties" : null
  }, {
    "href" : "https://i2.wp.com/img.abctruyen.xyz/uploads/18653/chuong-2/113.jpg",
    "type" : "image/jpeg",
    "bitrate" : 0,
    "duration" : 0,
    "title" : null,
    "properties" : null
  }, {
    "href" : "https://i2.wp.com/img.abctruyen.xyz/uploads/18653/chuong-2/114.jpg",
    "type" : "image/jpeg",
    "bitrate" : 0,
    "duration" : 0,
    "title" : null,
    "properties" : null
  }, {
    "href" : "https://i2.wp.com/img.abctruyen.xyz/uploads/18653/chuong-2/115.jpg",
    "type" : "image/jpeg",
    "bitrate" : 0,
    "duration" : 0,
    "title" : null,
    "properties" : null
  }, {
    "href" : "https://i2.wp.com/img.abctruyen.xyz/uploads/18653/chuong-2/116.jpg",
    "type" : "image/jpeg",
    "bitrate" : 0,
    "duration" : 0,
    "title" : null,
    "properties" : null
  }, {
    "href" : "https://i2.wp.com/img.abctruyen.xyz/uploads/18653/chuong-2/117.jpg",
    "type" : "image/jpeg",
    "bitrate" : 0,
    "duration" : 0,
    "title" : null,
    "properties" : null
  }, {
    "href" : "https://i2.wp.com/img.abctruyen.xyz/uploads/18653/chuong-2/118.jpg",
    "type" : "image/jpeg",
    "bitrate" : 0,
    "duration" : 0,
    "title" : null,
    "properties" : null
  }, {
    "href" : "https://i2.wp.com/img.abctruyen.xyz/uploads/18653/chuong-2/119.jpg",
    "type" : "image/jpeg",
    "bitrate" : 0,
    "duration" : 0,
    "title" : null,
    "properties" : null
  }, {
    "href" : "https://i2.wp.com/img.abctruyen.xyz/uploads/18653/chuong-2/120.jpg",
    "type" : "image/jpeg",
    "bitrate" : 0,
    "duration" : 0,
    "title" : null,
    "properties" : null
  }, {
    "href" : "https://i2.wp.com/img.abctruyen.xyz/uploads/18653/chuong-2/121.jpg",
    "type" : "image/jpeg",
    "bitrate" : 0,
    "duration" : 0,
    "title" : null,
    "properties" : null
  }, {
    "href" : "https://i2.wp.com/img.abctruyen.xyz/uploads/18653/chuong-2/122.jpg",
    "type" : "image/jpeg",
    "bitrate" : 0,
    "duration" : 0,
    "title" : null,
    "properties" : null
  }, {
    "href" : "https://i2.wp.com/img.abctruyen.xyz/uploads/18653/chuong-2/123.jpg",
    "type" : "image/jpeg",
    "bitrate" : 0,
    "duration" : 0,
    "title" : null,
    "properties" : null
  }, {
    "href" : "https://i2.wp.com/img.abctruyen.xyz/uploads/18653/chuong-2/124.jpg",
    "type" : "image/jpeg",
    "bitrate" : 0,
    "duration" : 0,
    "title" : null,
    "properties" : null
  }, {
    "href" : "https://i2.wp.com/img.abctruyen.xyz/uploads/18653/chuong-2/125.jpg",
    "type" : "image/jpeg",
    "bitrate" : 0,
    "duration" : 0,
    "title" : null,
    "properties" : null
  }, {
    "href" : "https://i2.wp.com/img.abctruyen.xyz/uploads/18653/chuong-2/126.jpg",
    "type" : "image/jpeg",
    "bitrate" : 0,
    "duration" : 0,
    "title" : null,
    "properties" : null
  }, {
    "href" : "https://i2.wp.com/img.abctruyen.xyz/uploads/18653/chuong-2/127.jpg",
    "type" : "image/jpeg",
    "bitrate" : 0,
    "duration" : 0,
    "title" : null,
    "properties" : null
  }, {
    "href" : "https://i2.wp.com/img.abctruyen.xyz/uploads/18653/chuong-2/128.jpg",
    "type" : "image/jpeg",
    "bitrate" : 0,
    "duration" : 0,
    "title" : null,
    "properties" : null
  }, {
    "href" : "https://i2.wp.com/img.abctruyen.xyz/uploads/18653/chuong-2/129.jpg",
    "type" : "image/jpeg",
    "bitrate" : 0,
    "duration" : 0,
    "title" : null,
    "properties" : null
  }, {
    "href" : "https://i2.wp.com/img.abctruyen.xyz/uploads/18653/chuong-2/130.jpg",
    "type" : "image/jpeg",
    "bitrate" : 0,
    "duration" : 0,
    "title" : null,
    "properties" : null
  }, {
    "href" : "https://i2.wp.com/img.abctruyen.xyz/uploads/18653/chuong-2/131.jpg",
    "type" : "image/jpeg",
    "bitrate" : 0,
    "duration" : 0,
    "title" : null,
    "properties" : null
  }, {
    "href" : "https://i2.wp.com/img.abctruyen.xyz/uploads/18653/chuong-2/132.jpg",
    "type" : "image/jpeg",
    "bitrate" : 0,
    "duration" : 0,
    "title" : null,
    "properties" : null
  }, {
    "href" : "https://i2.wp.com/img.abctruyen.xyz/uploads/18653/chuong-2/133.jpg",
    "type" : "image/jpeg",
    "bitrate" : 0,
    "duration" : 0,
    "title" : null,
    "properties" : null
  }, {
    "href" : "https://i2.wp.com/img.abctruyen.xyz/uploads/18653/chuong-2/134.jpg",
    "type" : "image/jpeg",
    "bitrate" : 0,
    "duration" : 0,
    "title" : null,
    "properties" : null
  }, {
    "href" : "https://i2.wp.com/img.abctruyen.xyz/uploads/18653/chuong-2/135.jpg",
    "type" : "image/jpeg",
    "bitrate" : 0,
    "duration" : 0,
    "title" : null,
    "properties" : null
  }, {
    "href" : "https://i2.wp.com/img.abctruyen.xyz/uploads/18653/chuong-2/136.jpg",
    "type" : "image/jpeg",
    "bitrate" : 0,
    "duration" : 0,
    "title" : null,
    "properties" : null
  }, {
    "href" : "https://i2.wp.com/img.abctruyen.xyz/uploads/18653/chuong-2/137.jpg",
    "type" : "image/jpeg",
    "bitrate" : 0,
    "duration" : 0,
    "title" : null,
    "properties" : null
  }, {
    "href" : "https://i2.wp.com/img.abctruyen.xyz/uploads/18653/chuong-2/138.jpg",
    "type" : "image/jpeg",
    "bitrate" : 0,
    "duration" : 0,
    "title" : null,
    "properties" : null
  }, {
    "href" : "https://i2.wp.com/img.abctruyen.xyz/uploads/18653/chuong-2/139.jpg",
    "type" : "image/jpeg",
    "bitrate" : 0,
    "duration" : 0,
    "title" : null,
    "properties" : null
  }, {
    "href" : "https://i2.wp.com/img.abctruyen.xyz/uploads/18653/chuong-2/140.jpg",
    "type" : "image/jpeg",
    "bitrate" : 0,
    "duration" : 0,
    "title" : null,
    "properties" : null
  }, {
    "href" : "https://i2.wp.com/img.abctruyen.xyz/uploads/18653/chuong-2/141.jpg",
    "type" : "image/jpeg",
    "bitrate" : 0,
    "duration" : 0,
    "title" : null,
    "properties" : null
  }, {
    "href" : "https://i2.wp.com/img.abctruyen.xyz/uploads/18653/chuong-2/142.jpg",
    "type" : "image/jpeg",
    "bitrate" : 0,
    "duration" : 0,
    "title" : null,
    "properties" : null
  }, {
    "href" : "https://i2.wp.com/img.abctruyen.xyz/uploads/18653/chuong-2/143.jpg",
    "type" : "image/jpeg",
    "bitrate" : 0,
    "duration" : 0,
    "title" : null,
    "properties" : null
  }, {
    "href" : "https://i2.wp.com/img.abctruyen.xyz/uploads/18653/chuong-2/144.jpg",
    "type" : "image/jpeg",
    "bitrate" : 0,
    "duration" : 0,
    "title" : null,
    "properties" : null
  }, {
    "href" : "https://i2.wp.com/img.abctruyen.xyz/uploads/18653/chuong-2/145.jpg",
    "type" : "image/jpeg",
    "bitrate" : 0,
    "duration" : 0,
    "title" : null,
    "properties" : null
  }, {
    "href" : "https://i2.wp.com/img.abctruyen.xyz/uploads/18653/chuong-2/146.jpg",
    "type" : "image/jpeg",
    "bitrate" : 0,
    "duration" : 0,
    "title" : null,
    "properties" : null
  }, {
    "href" : "https://i2.wp.com/img.abctruyen.xyz/uploads/18653/chuong-2/147.jpg",
    "type" : "image/jpeg",
    "bitrate" : 0,
    "duration" : 0,
    "title" : null,
    "properties" : null
  }, {
    "href" : "https://i2.wp.com/img.abctruyen.xyz/uploads/18653/chuong-2/148.jpg",
    "type" : "image/jpeg",
    "bitrate" : 0,
    "duration" : 0,
    "title" : null,
    "properties" : null
  }, {
    "href" : "https://i2.wp.com/img.abctruyen.xyz/uploads/18653/chuong-2/149.jpg",
    "type" : "image/jpeg",
    "bitrate" : 0,
    "duration" : 0,
    "title" : null,
    "properties" : null
  }, {
    "href" : "https://i2.wp.com/img.abctruyen.xyz/uploads/18653/chuong-2/150.jpg",
    "type" : "image/jpeg",
    "bitrate" : 0,
    "duration" : 0,
    "title" : null,
    "properties" : null
  }, {
    "href" : "https://i2.wp.com/img.abctruyen.xyz/uploads/18653/chuong-2/151.jpg",
    "type" : "image/jpeg",
    "bitrate" : 0,
    "duration" : 0,
    "title" : null,
    "properties" : null
  }, {
    "href" : "https://i2.wp.com/img.abctruyen.xyz/uploads/18653/chuong-2/152.jpg",
    "type" : "image/jpeg",
    "bitrate" : 0,
    "duration" : 0,
    "title" : null,
    "properties" : null
  }, {
    "href" : "https://i2.wp.com/img.abctruyen.xyz/uploads/18653/chuong-2/153.jpg",
    "type" : "image/jpeg",
    "bitrate" : 0,
    "duration" : 0,
    "title" : null,
    "properties" : null
  }, {
    "href" : "https://i2.wp.com/img.abctruyen.xyz/uploads/18653/chuong-2/154.jpg",
    "type" : "image/jpeg",
    "bitrate" : 0,
    "duration" : 0,
    "title" : null,
    "properties" : null
  }, {
    "href" : "https://i2.wp.com/img.abctruyen.xyz/uploads/18653/chuong-2/155.jpg",
    "type" : "image/jpeg",
    "bitrate" : 0,
    "duration" : 0,
    "title" : null,
    "properties" : null
  }, {
    "href" : "https://i2.wp.com/img.abctruyen.xyz/uploads/18653/chuong-2/156.jpg",
    "type" : "image/jpeg",
    "bitrate" : 0,
    "duration" : 0,
    "title" : null,
    "properties" : null
  }, {
    "href" : "https://i2.wp.com/img.abctruyen.xyz/uploads/18653/chuong-2/157.jpg",
    "type" : "image/jpeg",
    "bitrate" : 0,
    "duration" : 0,
    "title" : null,
    "properties" : null
  }, {
    "href" : "https://i2.wp.com/img.abctruyen.xyz/uploads/18653/chuong-2/158.jpg",
    "type" : "image/jpeg",
    "bitrate" : 0,
    "duration" : 0,
    "title" : null,
    "properties" : null
  }, {
    "href" : "https://i2.wp.com/img.abctruyen.xyz/uploads/18653/chuong-2/159.jpg",
    "type" : "image/jpeg",
    "bitrate" : 0,
    "duration" : 0,
    "title" : null,
    "properties" : null
  }, {
    "href" : "https://i2.wp.com/img.abctruyen.xyz/uploads/18653/chuong-2/160.jpg",
    "type" : "image/jpeg",
    "bitrate" : 0,
    "duration" : 0,
    "title" : null,
    "properties" : null
  }, {
    "href" : "https://i2.wp.com/img.abctruyen.xyz/uploads/18653/chuong-2/161.jpg",
    "type" : "image/jpeg",
    "bitrate" : 0,
    "duration" : 0,
    "title" : null,
    "properties" : null
  }, {
    "href" : "https://i2.wp.com/img.abctruyen.xyz/uploads/18653/chuong-2/162.jpg",
    "type" : "image/jpeg",
    "bitrate" : 0,
    "duration" : 0,
    "title" : null,
    "properties" : null
  }, {
    "href" : "https://i2.wp.com/img.abctruyen.xyz/uploads/18653/chuong-2/163.jpg",
    "type" : "image/jpeg",
    "bitrate" : 0,
    "duration" : 0,
    "title" : null,
    "properties" : null
  }, {
    "href" : "https://i2.wp.com/img.abctruyen.xyz/uploads/18653/chuong-2/164.jpg",
    "type" : "image/jpeg",
    "bitrate" : 0,
    "duration" : 0,
    "title" : null,
    "properties" : null
  }, {
    "href" : "https://i2.wp.com/img.abctruyen.xyz/uploads/18653/chuong-2/165.jpg",
    "type" : "image/jpeg",
    "bitrate" : 0,
    "duration" : 0,
    "title" : null,
    "properties" : null
  }, {
    "href" : "https://i2.wp.com/img.abctruyen.xyz/uploads/18653/chuong-2/166.jpg",
    "type" : "image/jpeg",
    "bitrate" : 0,
    "duration" : 0,
    "title" : null,
    "properties" : null
  }, {
    "href" : "https://i2.wp.com/img.abctruyen.xyz/uploads/18653/chuong-2/167.jpg",
    "type" : "image/jpeg",
    "bitrate" : 0,
    "duration" : 0,
    "title" : null,
    "properties" : null
  }, {
    "href" : "https://i2.wp.com/img.abctruyen.xyz/uploads/18653/chuong-2/168.jpg",
    "type" : "image/jpeg",
    "bitrate" : 0,
    "duration" : 0,
    "title" : null,
    "properties" : null
  }, {
    "href" : "https://i2.wp.com/img.abctruyen.xyz/uploads/18653/chuong-2/169.jpg",
    "type" : "image/jpeg",
    "bitrate" : 0,
    "duration" : 0,
    "title" : null,
    "properties" : null
  }, {
    "href" : "https://i2.wp.com/img.abctruyen.xyz/uploads/18653/chuong-2/170.jpg",
    "type" : "image/jpeg",
    "bitrate" : 0,
    "duration" : 0,
    "title" : null,
    "properties" : null
  }, {
    "href" : "https://i2.wp.com/img.abctruyen.xyz/uploads/18653/chuong-2/171.jpg",
    "type" : "image/jpeg",
    "bitrate" : 0,
    "duration" : 0,
    "title" : null,
    "properties" : null
  }, {
    "href" : "https://i2.wp.com/img.abctruyen.xyz/uploads/18653/chuong-2/172.jpg",
    "type" : "image/jpeg",
    "bitrate" : 0,
    "duration" : 0,
    "title" : null,
    "properties" : null
  }, {
    "href" : "https://i2.wp.com/img.abctruyen.xyz/uploads/18653/chuong-2/173.jpg",
    "type" : "image/jpeg",
    "bitrate" : 0,
    "duration" : 0,
    "title" : null,
    "properties" : null
  }, {
    "href" : "https://i2.wp.com/img.abctruyen.xyz/uploads/18653/chuong-2/174.jpg",
    "type" : "image/jpeg",
    "bitrate" : 0,
    "duration" : 0,
    "title" : null,
    "properties" : null
  }, {
    "href" : "https://i2.wp.com/img.abctruyen.xyz/uploads/18653/chuong-2/175.jpg",
    "type" : "image/jpeg",
    "bitrate" : 0,
    "duration" : 0,
    "title" : null,
    "properties" : null
  } ],
  "toc" : null,
  "@context" : "https://readium.org/webpub-manifest/context.jsonld"
}