{
  "metadata" : {
    "identifier" : "https://nghetruyenma.net/mau-nhuom-trinh-gia-2.html",
    "title" : "Máu Nhuộm Trịnh Gia",
    "subtitle" : "N/A",
    "author" : {
      "name" : "Việt Nga",
      "sortAs" : ""
    },
    "narrator" : "N/A",
    "language" : "vi",
    "description" : "N/A",
    "publisher" : "N/A",
    "subject" : null,
    "modified" : null,
    "published" : "2023-06-27",
    "duration" : 9517,
    "abridged" : false,
    "conformsTo" : null,
    "numberOfPages" : null,
    "readingProgression" : null,
    "belongsTo" : null,
    "presentation" : null,
    "@type" : "http://schema.org/Audiobook",
    "schema:license" : "https://creativecommons.org/publicdomain/zero/1.0/"
  },
  "links" : [ {
    "rel" : "self",
    "href" : "https://raw.githubusercontent.com/vietduyhuynh90s/book_storage_two7/main/EPUB/EPUB_51728e7dc63a5068071a2377af4822ca.json",
    "type" : "application/audiobook+json"
  }, {
    "rel" : "cover",
    "href" : "https://raw.githubusercontent.com/vietduyhuynh90s/book_storage_two7/main/IMAGE/IMAGE_51728e7dc63a5068071a2377af4822ca.webp",
    "type" : "image/jpeg",
    "height" : 300,
    "width" : 300
  } ],
  "readingOrder" : [ {
    "href" : "https://archive.org/download/mau-nhuom-trinh-gia/mau-nhuom-trinh-gia.mp3",
    "type" : "audio/mpeg",
    "bitrate" : 128,
    "duration" : 4635,
    "title" : "mau-nhuom-trinh-gia",
    "properties" : null,
    "alternate" : null
  }, {
    "href" : "https://archive.org/download/mau-nhuom-trinh-gia/mau-nhuom-trinh-gia-tap-2.mp3",
    "type" : "audio/mpeg",
    "bitrate" : 128,
    "duration" : 4882,
    "title" : "mau-nhuom-trinh-gia-tap-2",
    "properties" : null,
    "alternate" : null
  } ],
  "toc" : [ {
    "href" : "https://archive.org/download/mau-nhuom-trinh-gia/mau-nhuom-trinh-gia.mp3",
    "title" : "mau-nhuom-trinh-gia",
    "children" : [ ]
  }, {
    "href" : "https://archive.org/download/mau-nhuom-trinh-gia/mau-nhuom-trinh-gia-tap-2.mp3",
    "title" : "mau-nhuom-trinh-gia-tap-2",
    "children" : [ ]
  } ],
  "@context" : "https://readium.org/webpub-manifest/context.jsonld"
}